CHANGES.txt
MANIFEST.in
README.md
package.json
requirements.txt
setup.py
GeobricksCommon.egg-info/PKG-INFO
GeobricksCommon.egg-info/SOURCES.txt
GeobricksCommon.egg-info/dependency_links.txt
GeobricksCommon.egg-info/pbr.json
GeobricksCommon.egg-info/top_level.txt
geobricks_common/__init__.py
geobricks_common/__init__.pyc
geobricks_common/config/__init__.py
geobricks_common/config/__init__.pyc
geobricks_common/config/config.py
geobricks_common/config/config.pyc
geobricks_common/core/__init__.py
geobricks_common/core/__init__.pyc
geobricks_common/core/date.py
geobricks_common/core/date.pyc
geobricks_common/core/email_utils.py
geobricks_common/core/filesystem.py
geobricks_common/core/filesystem.pyc
geobricks_common/core/log.py
geobricks_common/core/log.pyc
geobricks_common/core/utils.py
geobricks_common/core/utils.pyc
geobricks_common/rest/__init__.py
geobricks_common/rest/__init__.pyc
geobricks_common/rest/common_main.py
geobricks_common/rest/common_rest.py
geobricks_common/rest/common_rest.pyc