Metadata-Version: 1.0
Name: GeobricksCommon
Version: 0.0.9
Summary: Geobricks common library.
Home-page: http://pypi.python.org/pypi/GeobricksCommon/
Author: Simone Murzilli; Guido Barbaglia
Author-email: geobrickspy@gmail.com
License: LICENSE.txt
Keywords: geobricks
Platform: UNKNOWN
